dagster_flyte/__init__.py
dagster_flyte/flyte_compiler.py
dagster_flyte/version.py
dagster_flyte_tests/__init__.py
dagster_flyte_tests/test_dagster_flyte.py
dagster_flyte_tests/test_version.py
dagster_flyte-0.9.15.dist-info/METADATA
dagster_flyte-0.9.15.dist-info/WHEEL
dagster_flyte-0.9.15.dist-info/top_level.txt
dagster_flyte-0.9.15.dist-info/RECORD
