Metadata-Version: 2.1
Name: dagster-flyte
Version: 0.9.15
Summary: A Dagster integration for flyte
Home-page: https://github.com/dagster-io/dagster/tree/master/python_modules/libraries/dagster-flyte
Author: Elementl
Author-email: hello@elementl.com
License: Apache-2.0
Platform: UNKNOWN
Classifier: Programming Language :: Python :: 2.7
Classifier: Programming Language :: Python :: 3.6
Classifier: Programming Language :: Python :: 3.7
Classifier: License :: OSI Approved :: Apache Software License
Classifier: Operating System :: OS Independent
Requires-Dist: dagster
Requires-Dist: flytekit (<0.13.0)
Requires-Dist: python-forge
